r2x/__init__.py
r2x/__main__.py
r2x/__version__.py
r2x/api.py
r2x/cli.py
r2x/cli_functions.py
r2x/config_models.py
r2x/config_scenario.py
r2x/config_utils.py
r2x/core.py
r2x/enums.py
r2x/exceptions.py
r2x/logger.py
r2x/runner.py
r2x/units.py
r2x/utils.py
r2x/validation.py
r2x/defaults/__init__.py
r2x/defaults/config.json
r2x/defaults/example_defaults_override.yml
r2x/defaults/mapping_schema.json
r2x/defaults/master_9.2R6_btu.xml
r2x/defaults/month_hrs.csv
r2x/defaults/pcm_defaults.json
r2x/defaults/plexos_horizons.json
r2x/defaults/plexos_input.json
r2x/defaults/plexos_mapping.json
r2x/defaults/plexos_models.json
r2x/defaults/plexos_output.json
r2x/defaults/plexos_reports.json
r2x/defaults/plexos_simulation_objects.json
r2x/defaults/plugins_config.json
r2x/defaults/reeds_india_input.json
r2x/defaults/reeds_india_mapping.json
r2x/defaults/reeds_input.json
r2x/defaults/reeds_us_mapping.json
r2x/defaults/sienna_config.json
r2x/defaults/sienna_mapping.json
r2x/defaults/user_dict.yaml
r2x/exporter/__init__.py
r2x/exporter/handler.py
r2x/exporter/plexos.py
r2x/exporter/sienna.py
r2x/exporter/utils.py
r2x/models/__init__.py
r2x/models/attributes.py
r2x/models/branch.py
r2x/models/core.py
r2x/models/costs.py
r2x/models/generators.py
r2x/models/load.py
r2x/models/named_tuples.py
r2x/models/services.py
r2x/models/topology.py
r2x/models/utils.py
r2x/parser/__init__.py
r2x/parser/handler.py
r2x/parser/handler_utils.py
r2x/parser/parser_helpers.py
r2x/parser/plexos.py
r2x/parser/plexos_utils.py
r2x/parser/polars_helpers.py
r2x/parser/reeds.py
r2x/plugins/__init__.py
r2x/plugins/break_gens.py
r2x/plugins/cambium.py
r2x/plugins/ccs_credit.py
r2x/plugins/electrolyzer.py
r2x/plugins/emission_cap.py
r2x/plugins/hurdle_rate.py
r2x/plugins/imports.py
r2x/plugins/pcm_defaults.py
r2x/plugins/utils.py
r2x/upgrader/__init__.py
r2x/upgrader/checks.py
r2x/upgrader/file_tracker.csv
r2x/upgrader/functions.py
r2x/upgrader/helpers.py
r2x-1.2.0.dist-info/METADATA
r2x-1.2.0.dist-info/WHEEL
r2x-1.2.0.dist-info/entry_points.txt
r2x-1.2.0.dist-info/licenses/LICENCE.txt
r2x-1.2.0.dist-info/RECORD
