Metadata-Version: 2.4
Name: r2x
Version: 1.2.0
Summary: ReEDS to X parser
Author-email: Pedro Sanchez <psanchez@nrel.gov>, Obika Kodi <kodi.obika@nrel.gov>, Vivienne Liu <vivienne.liu@nrel.gov>
License-File: LICENCE.txt
Classifier: Development Status :: 4 - Beta
Classifier: Intended Audience :: Developers
Classifier: License :: OSI Approved :: BSD License
Classifier: Operating System :: OS Independent
Classifier: Programming Language :: Python :: 3.11
Classifier: Programming Language :: Python :: 3.12
Classifier: Topic :: Software Development :: Build Tools
Requires-Python: <3.13,>=3.11
Requires-Dist: cvxpy~=1.5.3
Requires-Dist: h5py
Requires-Dist: infrasys~=0.4.0
Requires-Dist: jsonschema~=4.23
Requires-Dist: loguru~=0.7.2
Requires-Dist: pandas>=2.2
Requires-Dist: plexosdb~=0.1.0
Requires-Dist: polars~=1.1.0
Requires-Dist: pyyaml~=6.0.1
Requires-Dist: rich~=13.7.1
Requires-Dist: tables~=3.10.1
